{"cameraMode":{"drawMode":0,"name":"Shaded","section":"Shading Mode"},"sceneLighting":true,"audioPlay":false,"sceneViewState":{"showFog":true,"showMaterialUpdate":false,"showSkybox":true,"showFlares":true,"showImageEffects":true,"showParticleSystems":true},"in2DMode":false,"pivot":{"x":4.924256324768066,"y":-10.730489730834961,"z":26.285625457763673},"rotation":{"x":0.1785237193107605,"y":0.07401113957166672,"z":-0.01346679963171482,"w":0.9810634255409241},"size":57.765316009521487,"orthographic":false}